{
  "DLSVersion": "2.1.6",
  "Name": "NAND-30",
  "NameLocation": 0,
  "ChipType": 0,
  "Size": {
    "x": 2.075,
    "y": 4.5
  },
  "Colour": {
    "r": 0.8784313725490196,
    "g": 0.47058823529411764,
    "b": 0.1411764705882353,
    "a": 1
  },
  "InputPins": [
    {
      "Name": "IN",
      "ID": 746357553,
      "Position": {
        "x": 0,
        "y": 7.25
      },
      "BitCount": 1,
      "Colour": 0,
      "ValueDisplayMode": 0
    },
    {
      "Name": "IN",
      "ID": 864766376,
      "Position": {
        "x": 0,
        "y": 6.75
      },
      "BitCount": 1,
      "Colour": 0,
      "ValueDisplayMode": 0
    },
    {
      "Name": "IN",
      "ID": 425679071,
      "Position": {
        "x": 0,
        "y": 6.25
      },
      "BitCount": 1,
      "Colour": 0,
      "ValueDisplayMode": 0
    },
    {
      "Name": "IN",
      "ID": 1965203707,
      "Position": {
        "x": 0,
        "y": 5.75
      },
      "BitCount": 1,
      "Colour": 0,
      "ValueDisplayMode": 0
    },
    {
      "Name": "IN",
      "ID": 1597506863,
      "Position": {
        "x": 0,
        "y": 5.25
      },
      "BitCount": 1,
      "Colour": 0,
      "ValueDisplayMode": 0
    },
    {
      "Name": "IN",
      "ID": 858871299,
      "Position": {
        "x": 0,
        "y": 4.75
      },
      "BitCount": 1,
      "Colour": 0,
      "ValueDisplayMode": 0
    },
    {
      "Name": "IN",
      "ID": 1625586269,
      "Position": {
        "x": 0,
        "y": 4.25
      },
      "BitCount": 1,
      "Colour": 0,
      "ValueDisplayMode": 0
    },
    {
      "Name": "IN",
      "ID": 625126601,
      "Position": {
        "x": 0,
        "y": 3.75
      },
      "BitCount": 1,
      "Colour": 0,
      "ValueDisplayMode": 0
    },
    {
      "Name": "IN",
      "ID": 611713002,
      "Position": {
        "x": 0,
        "y": 3.25
      },
      "BitCount": 1,
      "Colour": 0,
      "ValueDisplayMode": 0
    },
    {
      "Name": "IN",
      "ID": 493536560,
      "Position": {
        "x": 0,
        "y": 2.75
      },
      "BitCount": 1,
      "Colour": 0,
      "ValueDisplayMode": 0
    },
    {
      "Name": "IN",
      "ID": 1393403944,
      "Position": {
        "x": 0,
        "y": 2.25
      },
      "BitCount": 1,
      "Colour": 0,
      "ValueDisplayMode": 0
    },
    {
      "Name": "IN",
      "ID": 448870765,
      "Position": {
        "x": 0,
        "y": 1.75
      },
      "BitCount": 1,
      "Colour": 0,
      "ValueDisplayMode": 0
    },
    {
      "Name": "IN",
      "ID": 728777688,
      "Position": {
        "x": 0,
        "y": 1.25
      },
      "BitCount": 1,
      "Colour": 0,
      "ValueDisplayMode": 0
    },
    {
      "Name": "IN",
      "ID": 167794193,
      "Position": {
        "x": 0,
        "y": 0.75
      },
      "BitCount": 1,
      "Colour": 0,
      "ValueDisplayMode": 0
    },
    {
      "Name": "IN",
      "ID": 996164970,
      "Position": {
        "x": 0,
        "y": 0.25
      },
      "BitCount": 1,
      "Colour": 0,
      "ValueDisplayMode": 0
    },
    {
      "Name": "IN",
      "ID": 1259995701,
      "Position": {
        "x": 0,
        "y": -0.25
      },
      "BitCount": 1,
      "Colour": 0,
      "ValueDisplayMode": 0
    },
    {
      "Name": "IN",
      "ID": 480397395,
      "Position": {
        "x": 0,
        "y": -0.75
      },
      "BitCount": 1,
      "Colour": 0,
      "ValueDisplayMode": 0
    },
    {
      "Name": "IN",
      "ID": 216263051,
      "Position": {
        "x": 0,
        "y": -1.25
      },
      "BitCount": 1,
      "Colour": 0,
      "ValueDisplayMode": 0
    },
    {
      "Name": "IN",
      "ID": 1540025944,
      "Position": {
        "x": 0,
        "y": -1.75
      },
      "BitCount": 1,
      "Colour": 0,
      "ValueDisplayMode": 0
    },
    {
      "Name": "IN",
      "ID": 1524622573,
      "Position": {
        "x": 0,
        "y": -2.25
      },
      "BitCount": 1,
      "Colour": 0,
      "ValueDisplayMode": 0
    },
    {
      "Name": "IN",
      "ID": 1336821477,
      "Position": {
        "x": 0,
        "y": -2.75
      },
      "BitCount": 1,
      "Colour": 0,
      "ValueDisplayMode": 0
    },
    {
      "Name": "IN",
      "ID": 437184160,
      "Position": {
        "x": 0,
        "y": -3.25
      },
      "BitCount": 1,
      "Colour": 0,
      "ValueDisplayMode": 0
    },
    {
      "Name": "IN",
      "ID": 825872456,
      "Position": {
        "x": 0,
        "y": -3.75
      },
      "BitCount": 1,
      "Colour": 0,
      "ValueDisplayMode": 0
    },
    {
      "Name": "IN",
      "ID": 1280487941,
      "Position": {
        "x": 0,
        "y": -4.25
      },
      "BitCount": 1,
      "Colour": 0,
      "ValueDisplayMode": 0
    },
    {
      "Name": "IN",
      "ID": 774388812,
      "Position": {
        "x": 0,
        "y": -4.75
      },
      "BitCount": 1,
      "Colour": 0,
      "ValueDisplayMode": 0
    },
    {
      "Name": "IN",
      "ID": 984486587,
      "Position": {
        "x": 0,
        "y": -5.25
      },
      "BitCount": 1,
      "Colour": 0,
      "ValueDisplayMode": 0
    },
    {
      "Name": "IN",
      "ID": 180723878,
      "Position": {
        "x": 0,
        "y": -5.75
      },
      "BitCount": 1,
      "Colour": 0,
      "ValueDisplayMode": 0
    },
    {
      "Name": "IN",
      "ID": 685411404,
      "Position": {
        "x": 0,
        "y": -6.25
      },
      "BitCount": 1,
      "Colour": 0,
      "ValueDisplayMode": 0
    },
    {
      "Name": "IN",
      "ID": 1272759553,
      "Position": {
        "x": 0,
        "y": -6.75
      },
      "BitCount": 1,
      "Colour": 0,
      "ValueDisplayMode": 0
    },
    {
      "Name": "IN",
      "ID": 85966576,
      "Position": {
        "x": 0,
        "y": -7.25
      },
      "BitCount": 1,
      "Colour": 0,
      "ValueDisplayMode": 0
    }
  ],
  "OutputPins": [
    {
      "Name": "OUT",
      "ID": 1698926522,
      "Position": {
        "x": 14,
        "y": 0
      },
      "BitCount": 1,
      "Colour": 0,
      "ValueDisplayMode": 0
    }
  ],
  "SubChips": [
    {
      "Name": "AND",
      "ID": 1116572725,
      "Label": "",
      "Position": {
        "x": 2,
        "y": 4.8999999999999995
      },
      "OutputPinColourInfo": [
        {
          "PinColour": 0,
          "PinID": 2075686198
        }
      ],
      "InternalData": null
    },
    {
      "Name": "AND",
      "ID": 318589364,
      "Label": "",
      "Position": {
        "x": 2,
        "y": 4.2
      },
      "OutputPinColourInfo": [
        {
          "PinColour": 0,
          "PinID": 2075686198
        }
      ],
      "InternalData": null
    },
    {
      "Name": "AND",
      "ID": 1120125273,
      "Label": "",
      "Position": {
        "x": 2,
        "y": 3.5
      },
      "OutputPinColourInfo": [
        {
          "PinColour": 0,
          "PinID": 2075686198
        }
      ],
      "InternalData": null
    },
    {
      "Name": "AND",
      "ID": 769852393,
      "Label": "",
      "Position": {
        "x": 2,
        "y": 2.8
      },
      "OutputPinColourInfo": [
        {
          "PinColour": 0,
          "PinID": 2075686198
        }
      ],
      "InternalData": null
    },
    {
      "Name": "AND",
      "ID": 68666773,
      "Label": "",
      "Position": {
        "x": 2,
        "y": 2.0999999999999996
      },
      "OutputPinColourInfo": [
        {
          "PinColour": 0,
          "PinID": 2075686198
        }
      ],
      "InternalData": null
    },
    {
      "Name": "AND",
      "ID": 795275260,
      "Label": "",
      "Position": {
        "x": 2,
        "y": 1.3999999999999995
      },
      "OutputPinColourInfo": [
        {
          "PinColour": 0,
          "PinID": 2075686198
        }
      ],
      "InternalData": null
    },
    {
      "Name": "AND",
      "ID": 1715354987,
      "Label": "",
      "Position": {
        "x": 2,
        "y": 0.6999999999999994
      },
      "OutputPinColourInfo": [
        {
          "PinColour": 0,
          "PinID": 2075686198
        }
      ],
      "InternalData": null
    },
    {
      "Name": "AND",
      "ID": 1016307063,
      "Label": "",
      "Position": {
        "x": 2,
        "y": -5.551115123125783e-16
      },
      "OutputPinColourInfo": [
        {
          "PinColour": 0,
          "PinID": 2075686198
        }
      ],
      "InternalData": null
    },
    {
      "Name": "AND",
      "ID": 126803588,
      "Label": "",
      "Position": {
        "x": 2,
        "y": -0.7000000000000005
      },
      "OutputPinColourInfo": [
        {
          "PinColour": 0,
          "PinID": 2075686198
        }
      ],
      "InternalData": null
    },
    {
      "Name": "AND",
      "ID": 1469145571,
      "Label": "",
      "Position": {
        "x": 2,
        "y": -1.4000000000000004
      },
      "OutputPinColourInfo": [
        {
          "PinColour": 0,
          "PinID": 2075686198
        }
      ],
      "InternalData": null
    },
    {
      "Name": "AND",
      "ID": 1025654058,
      "Label": "",
      "Position": {
        "x": 2,
        "y": -2.1000000000000005
      },
      "OutputPinColourInfo": [
        {
          "PinColour": 0,
          "PinID": 2075686198
        }
      ],
      "InternalData": null
    },
    {
      "Name": "AND",
      "ID": 1204463035,
      "Label": "",
      "Position": {
        "x": 2,
        "y": -2.8000000000000007
      },
      "OutputPinColourInfo": [
        {
          "PinColour": 0,
          "PinID": 2075686198
        }
      ],
      "InternalData": null
    },
    {
      "Name": "AND",
      "ID": 1892717237,
      "Label": "",
      "Position": {
        "x": 2,
        "y": -3.500000000000001
      },
      "OutputPinColourInfo": [
        {
          "PinColour": 0,
          "PinID": 2075686198
        }
      ],
      "InternalData": null
    },
    {
      "Name": "AND",
      "ID": 888382623,
      "Label": "",
      "Position": {
        "x": 2,
        "y": -4.200000000000001
      },
      "OutputPinColourInfo": [
        {
          "PinColour": 0,
          "PinID": 2075686198
        }
      ],
      "InternalData": null
    },
    {
      "Name": "AND",
      "ID": 1298487732,
      "Label": "",
      "Position": {
        "x": 2,
        "y": -4.9
      },
      "OutputPinColourInfo": [
        {
          "PinColour": 0,
          "PinID": 2075686198
        }
      ],
      "InternalData": null
    },
    {
      "Name": "AND",
      "ID": 1230984279,
      "Label": "",
      "Position": {
        "x": 4,
        "y": 2.1
      },
      "OutputPinColourInfo": [
        {
          "PinColour": 0,
          "PinID": 2075686198
        }
      ],
      "InternalData": null
    },
    {
      "Name": "AND",
      "ID": 1009138828,
      "Label": "",
      "Position": {
        "x": 4,
        "y": 1.4
      },
      "OutputPinColourInfo": [
        {
          "PinColour": 0,
          "PinID": 2075686198
        }
      ],
      "InternalData": null
    },
    {
      "Name": "AND",
      "ID": 865562477,
      "Label": "",
      "Position": {
        "x": 4,
        "y": 0.6999999999999998
      },
      "OutputPinColourInfo": [
        {
          "PinColour": 0,
          "PinID": 2075686198
        }
      ],
      "InternalData": null
    },
    {
      "Name": "AND",
      "ID": 1541698629,
      "Label": "",
      "Position": {
        "x": 4,
        "y": -1.1102230246251565e-16
      },
      "OutputPinColourInfo": [
        {
          "PinColour": 0,
          "PinID": 2075686198
        }
      ],
      "InternalData": null
    },
    {
      "Name": "AND",
      "ID": 1003649762,
      "Label": "",
      "Position": {
        "x": 4,
        "y": -0.7000000000000001
      },
      "OutputPinColourInfo": [
        {
          "PinColour": 0,
          "PinID": 2075686198
        }
      ],
      "InternalData": null
    },
    {
      "Name": "AND",
      "ID": 164299224,
      "Label": "",
      "Position": {
        "x": 4,
        "y": -1.4
      },
      "OutputPinColourInfo": [
        {
          "PinColour": 0,
          "PinID": 2075686198
        }
      ],
      "InternalData": null
    },
    {
      "Name": "AND",
      "ID": 308888300,
      "Label": "",
      "Position": {
        "x": 4,
        "y": -2.1
      },
      "OutputPinColourInfo": [
        {
          "PinColour": 0,
          "PinID": 2075686198
        }
      ],
      "InternalData": null
    },
    {
      "Name": "AND",
      "ID": 1744496387,
      "Label": "",
      "Position": {
        "x": 6,
        "y": 1.0499999999999998
      },
      "OutputPinColourInfo": [
        {
          "PinColour": 0,
          "PinID": 2075686198
        }
      ],
      "InternalData": null
    },
    {
      "Name": "AND",
      "ID": 1485368144,
      "Label": "",
      "Position": {
        "x": 6,
        "y": 0.34999999999999987
      },
      "OutputPinColourInfo": [
        {
          "PinColour": 0,
          "PinID": 2075686198
        }
      ],
      "InternalData": null
    },
    {
      "Name": "AND",
      "ID": 1611270583,
      "Label": "",
      "Position": {
        "x": 6,
        "y": -0.3500000000000001
      },
      "OutputPinColourInfo": [
        {
          "PinColour": 0,
          "PinID": 2075686198
        }
      ],
      "InternalData": null
    },
    {
      "Name": "AND",
      "ID": 2020794374,
      "Label": "",
      "Position": {
        "x": 6,
        "y": -1.05
      },
      "OutputPinColourInfo": [
        {
          "PinColour": 0,
          "PinID": 2075686198
        }
      ],
      "InternalData": null
    },
    {
      "Name": "AND",
      "ID": 953573564,
      "Label": "",
      "Position": {
        "x": 8,
        "y": 0.35
      },
      "OutputPinColourInfo": [
        {
          "PinColour": 0,
          "PinID": 2075686198
        }
      ],
      "InternalData": null
    },
    {
      "Name": "AND",
      "ID": 1387814447,
      "Label": "",
      "Position": {
        "x": 8,
        "y": -0.35
      },
      "OutputPinColourInfo": [
        {
          "PinColour": 0,
          "PinID": 2075686198
        }
      ],
      "InternalData": null
    },
    {
      "Name": "AND",
      "ID": 394161708,
      "Label": "",
      "Position": {
        "x": 10,
        "y": 0
      },
      "OutputPinColourInfo": [
        {
          "PinColour": 0,
          "PinID": 2075686198
        }
      ],
      "InternalData": null
    },
    {
      "Name": "NOT",
      "ID": 1407689217,
      "Label": "",
      "Position": {
        "x": 12,
        "y": 0
      },
      "OutputPinColourInfo": [
        {
          "PinColour": 0,
          "PinID": 528329037
        }
      ],
      "InternalData": null
    }
  ],
  "Wires": [
    {
      "SourcePinAddress": {
        "PinID": 0,
        "PinOwnerID": 746357553
      },
      "TargetPinAddress": {
        "PinID": 1367873140,
        "PinOwnerID": 1116572725
      },
      "ConnectionType": 0,
      "ConnectedWireIndex": -1,
      "ConnectedWireSegmentIndex": -1,
      "Points": [
        {
          "x": 0,
          "y": 0
        },
        {
          "x": 0.5137499999999999,
          "y": 7.25
        },
        {
          "x": 0.5137499999999999,
          "y": 5.1499999999999995
        },
        {
          "x": 0,
          "y": 0
        }
      ]
    },
    {
      "SourcePinAddress": {
        "PinID": 0,
        "PinOwnerID": 864766376
      },
      "TargetPinAddress": {
        "PinID": 1311157128,
        "PinOwnerID": 1116572725
      },
      "ConnectionType": 0,
      "ConnectedWireIndex": -1,
      "ConnectedWireSegmentIndex": -1,
      "Points": [
        {
          "x": 0,
          "y": 0
        },
        {
          "x": 0.6421874999999999,
          "y": 6.75
        },
        {
          "x": 0.6421874999999999,
          "y": 4.6499999999999995
        },
        {
          "x": 0,
          "y": 0
        }
      ]
    },
    {
      "SourcePinAddress": {
        "PinID": 0,
        "PinOwnerID": 425679071
      },
      "TargetPinAddress": {
        "PinID": 1367873140,
        "PinOwnerID": 318589364
      },
      "ConnectionType": 0,
      "ConnectedWireIndex": -1,
      "ConnectedWireSegmentIndex": -1,
      "Points": [
        {
          "x": 0,
          "y": 0
        },
        {
          "x": 0.7706249999999999,
          "y": 6.25
        },
        {
          "x": 0.7706249999999999,
          "y": 4.45
        },
        {
          "x": 0,
          "y": 0
        }
      ]
    },
    {
      "SourcePinAddress": {
        "PinID": 0,
        "PinOwnerID": 1965203707
      },
      "TargetPinAddress": {
        "PinID": 1311157128,
        "PinOwnerID": 318589364
      },
      "ConnectionType": 0,
      "ConnectedWireIndex": -1,
      "ConnectedWireSegmentIndex": -1,
      "Points": [
        {
          "x": 0,
          "y": 0
        },
        {
          "x": 0.8990625,
          "y": 5.75
        },
        {
          "x": 0.8990625,
          "y": 3.95
        },
        {
          "x": 0,
          "y": 0
        }
      ]
    },
    {
      "SourcePinAddress": {
        "PinID": 0,
        "PinOwnerID": 1597506863
      },
      "TargetPinAddress": {
        "PinID": 1367873140,
        "PinOwnerID": 1120125273
      },
      "ConnectionType": 0,
      "ConnectedWireIndex": -1,
      "ConnectedWireSegmentIndex": -1,
      "Points": [
        {
          "x": 0,
          "y": 0
        },
        {
          "x": 1.0274999999999999,
          "y": 5.25
        },
        {
          "x": 1.0274999999999999,
          "y": 3.75
        },
        {
          "x": 0,
          "y": 0
        }
      ]
    },
    {
      "SourcePinAddress": {
        "PinID": 0,
        "PinOwnerID": 858871299
      },
      "TargetPinAddress": {
        "PinID": 1311157128,
        "PinOwnerID": 1120125273
      },
      "ConnectionType": 0,
      "ConnectedWireIndex": -1,
      "ConnectedWireSegmentIndex": -1,
      "Points": [
        {
          "x": 0,
          "y": 0
        },
        {
          "x": 1.1559375,
          "y": 4.75
        },
        {
          "x": 1.1559375,
          "y": 3.25
        },
        {
          "x": 0,
          "y": 0
        }
      ]
    },
    {
      "SourcePinAddress": {
        "PinID": 0,
        "PinOwnerID": 1625586269
      },
      "TargetPinAddress": {
        "PinID": 1367873140,
        "PinOwnerID": 769852393
      },
      "ConnectionType": 0,
      "ConnectedWireIndex": -1,
      "ConnectedWireSegmentIndex": -1,
      "Points": [
        {
          "x": 0,
          "y": 0
        },
        {
          "x": 0.5137499999999999,
          "y": 4.25
        },
        {
          "x": 0.5137499999999999,
          "y": 3.05
        },
        {
          "x": 0,
          "y": 0
        }
      ]
    },
    {
      "SourcePinAddress": {
        "PinID": 0,
        "PinOwnerID": 625126601
      },
      "TargetPinAddress": {
        "PinID": 1311157128,
        "PinOwnerID": 769852393
      },
      "ConnectionType": 0,
      "ConnectedWireIndex": -1,
      "ConnectedWireSegmentIndex": -1,
      "Points": [
        {
          "x": 0,
          "y": 0
        },
        {
          "x": 0.6421874999999999,
          "y": 3.75
        },
        {
          "x": 0.6421874999999999,
          "y": 2.55
        },
        {
          "x": 0,
          "y": 0
        }
      ]
    },
    {
      "SourcePinAddress": {
        "PinID": 0,
        "PinOwnerID": 611713002
      },
      "TargetPinAddress": {
        "PinID": 1367873140,
        "PinOwnerID": 68666773
      },
      "ConnectionType": 0,
      "ConnectedWireIndex": -1,
      "ConnectedWireSegmentIndex": -1,
      "Points": [
        {
          "x": 0,
          "y": 0
        },
        {
          "x": 0.7706249999999999,
          "y": 3.25
        },
        {
          "x": 0.7706249999999999,
          "y": 2.3499999999999996
        },
        {
          "x": 0,
          "y": 0
        }
      ]
    },
    {
      "SourcePinAddress": {
        "PinID": 0,
        "PinOwnerID": 493536560
      },
      "TargetPinAddress": {
        "PinID": 1311157128,
        "PinOwnerID": 68666773
      },
      "ConnectionType": 0,
      "ConnectedWireIndex": -1,
      "ConnectedWireSegmentIndex": -1,
      "Points": [
        {
          "x": 0,
          "y": 0
        },
        {
          "x": 0.8990625,
          "y": 2.75
        },
        {
          "x": 0.8990625,
          "y": 1.8499999999999996
        },
        {
          "x": 0,
          "y": 0
        }
      ]
    },
    {
      "SourcePinAddress": {
        "PinID": 0,
        "PinOwnerID": 1393403944
      },
      "TargetPinAddress": {
        "PinID": 1367873140,
        "PinOwnerID": 795275260
      },
      "ConnectionType": 0,
      "ConnectedWireIndex": -1,
      "ConnectedWireSegmentIndex": -1,
      "Points": [
        {
          "x": 0,
          "y": 0
        },
        {
          "x": 1.0274999999999999,
          "y": 2.25
        },
        {
          "x": 1.0274999999999999,
          "y": 1.6499999999999995
        },
        {
          "x": 0,
          "y": 0
        }
      ]
    },
    {
      "SourcePinAddress": {
        "PinID": 0,
        "PinOwnerID": 448870765
      },
      "TargetPinAddress": {
        "PinID": 1311157128,
        "PinOwnerID": 795275260
      },
      "ConnectionType": 0,
      "ConnectedWireIndex": -1,
      "ConnectedWireSegmentIndex": -1,
      "Points": [
        {
          "x": 0,
          "y": 0
        },
        {
          "x": 1.1559375,
          "y": 1.75
        },
        {
          "x": 1.1559375,
          "y": 1.1499999999999995
        },
        {
          "x": 0,
          "y": 0
        }
      ]
    },
    {
      "SourcePinAddress": {
        "PinID": 0,
        "PinOwnerID": 728777688
      },
      "TargetPinAddress": {
        "PinID": 1367873140,
        "PinOwnerID": 1715354987
      },
      "ConnectionType": 0,
      "ConnectedWireIndex": -1,
      "ConnectedWireSegmentIndex": -1,
      "Points": [
        {
          "x": 0,
          "y": 0
        },
        {
          "x": 0.5137499999999999,
          "y": 1.25
        },
        {
          "x": 0.5137499999999999,
          "y": 0.9499999999999994
        },
        {
          "x": 0,
          "y": 0
        }
      ]
    },
    {
      "SourcePinAddress": {
        "PinID": 0,
        "PinOwnerID": 167794193
      },
      "TargetPinAddress": {
        "PinID": 1311157128,
        "PinOwnerID": 1715354987
      },
      "ConnectionType": 0,
      "ConnectedWireIndex": -1,
      "ConnectedWireSegmentIndex": -1,
      "Points": [
        {
          "x": 0,
          "y": 0
        },
        {
          "x": 0.6421874999999999,
          "y": 0.75
        },
        {
          "x": 0.6421874999999999,
          "y": 0.4499999999999994
        },
        {
          "x": 0,
          "y": 0
        }
      ]
    },
    {
      "SourcePinAddress": {
        "PinID": 0,
        "PinOwnerID": 996164970
      },
      "TargetPinAddress": {
        "PinID": 1367873140,
        "PinOwnerID": 1016307063
      },
      "ConnectionType": 0,
      "ConnectedWireIndex": -1,
      "ConnectedWireSegmentIndex": -1,
      "Points": [
        {
          "x": 0,
          "y": 0
        },
        {
          "x": 0,
          "y": 0
        }
      ]
    },
    {
      "SourcePinAddress": {
        "PinID": 0,
        "PinOwnerID": 1259995701
      },
      "TargetPinAddress": {
        "PinID": 1311157128,
        "PinOwnerID": 1016307063
      },
      "ConnectionType": 0,
      "ConnectedWireIndex": -1,
      "ConnectedWireSegmentIndex": -1,
      "Points": [
        {
          "x": 0,
          "y": 0
        },
        {
          "x": 0,
          "y": 0
        }
      ]
    },
    {
      "SourcePinAddress": {
        "PinID": 0,
        "PinOwnerID": 480397395
      },
      "TargetPinAddress": {
        "PinID": 1367873140,
        "PinOwnerID": 126803588
      },
      "ConnectionType": 0,
      "ConnectedWireIndex": -1,
      "ConnectedWireSegmentIndex": -1,
      "Points": [
        {
          "x": 0,
          "y": 0
        },
        {
          "x": 0.7706249999999999,
          "y": -0.75
        },
        {
          "x": 0.7706249999999999,
          "y": -0.4500000000000005
        },
        {
          "x": 0,
          "y": 0
        }
      ]
    },
    {
      "SourcePinAddress": {
        "PinID": 0,
        "PinOwnerID": 216263051
      },
      "TargetPinAddress": {
        "PinID": 1311157128,
        "PinOwnerID": 126803588
      },
      "ConnectionType": 0,
      "ConnectedWireIndex": -1,
      "ConnectedWireSegmentIndex": -1,
      "Points": [
        {
          "x": 0,
          "y": 0
        },
        {
          "x": 0.8990625,
          "y": -1.25
        },
        {
          "x": 0.8990625,
          "y": -0.9500000000000005
        },
        {
          "x": 0,
          "y": 0
        }
      ]
    },
    {
      "SourcePinAddress": {
        "PinID": 0,
        "PinOwnerID": 1540025944
      },
      "TargetPinAddress": {
        "PinID": 1367873140,
        "PinOwnerID": 1469145571
      },
      "ConnectionType": 0,
      "ConnectedWireIndex": -1,
      "ConnectedWireSegmentIndex": -1,
      "Points": [
        {
          "x": 0,
          "y": 0
        },
        {
          "x": 1.0274999999999999,
          "y": -1.75
        },
        {
          "x": 1.0274999999999999,
          "y": -1.1500000000000004
        },
        {
          "x": 0,
          "y": 0
        }
      ]
    },
    {
      "SourcePinAddress": {
        "PinID": 0,
        "PinOwnerID": 1524622573
      },
      "TargetPinAddress": {
        "PinID": 1311157128,
        "PinOwnerID": 1469145571
      },
      "ConnectionType": 0,
      "ConnectedWireIndex": -1,
      "ConnectedWireSegmentIndex": -1,
      "Points": [
        {
          "x": 0,
          "y": 0
        },
        {
          "x": 1.1559375,
          "y": -2.25
        },
        {
          "x": 1.1559375,
          "y": -1.6500000000000004
        },
        {
          "x": 0,
          "y": 0
        }
      ]
    },
    {
      "SourcePinAddress": {
        "PinID": 0,
        "PinOwnerID": 1336821477
      },
      "TargetPinAddress": {
        "PinID": 1367873140,
        "PinOwnerID": 1025654058
      },
      "ConnectionType": 0,
      "ConnectedWireIndex": -1,
      "ConnectedWireSegmentIndex": -1,
      "Points": [
        {
          "x": 0,
          "y": 0
        },
        {
          "x": 0.5137499999999999,
          "y": -2.75
        },
        {
          "x": 0.5137499999999999,
          "y": -1.8500000000000005
        },
        {
          "x": 0,
          "y": 0
        }
      ]
    },
    {
      "SourcePinAddress": {
        "PinID": 0,
        "PinOwnerID": 437184160
      },
      "TargetPinAddress": {
        "PinID": 1311157128,
        "PinOwnerID": 1025654058
      },
      "ConnectionType": 0,
      "ConnectedWireIndex": -1,
      "ConnectedWireSegmentIndex": -1,
      "Points": [
        {
          "x": 0,
          "y": 0
        },
        {
          "x": 0.6421874999999999,
          "y": -3.25
        },
        {
          "x": 0.6421874999999999,
          "y": -2.3500000000000005
        },
        {
          "x": 0,
          "y": 0
        }
      ]
    },
    {
      "SourcePinAddress": {
        "PinID": 0,
        "PinOwnerID": 825872456
      },
      "TargetPinAddress": {
        "PinID": 1367873140,
        "PinOwnerID": 1204463035
      },
      "ConnectionType": 0,
      "ConnectedWireIndex": -1,
      "ConnectedWireSegmentIndex": -1,
      "Points": [
        {
          "x": 0,
          "y": 0
        },
        {
          "x": 0.7706249999999999,
          "y": -3.75
        },
        {
          "x": 0.7706249999999999,
          "y": -2.5500000000000007
        },
        {
          "x": 0,
          "y": 0
        }
      ]
    },
    {
      "SourcePinAddress": {
        "PinID": 0,
        "PinOwnerID": 1280487941
      },
      "TargetPinAddress": {
        "PinID": 1311157128,
        "PinOwnerID": 1204463035
      },
      "ConnectionType": 0,
      "ConnectedWireIndex": -1,
      "ConnectedWireSegmentIndex": -1,
      "Points": [
        {
          "x": 0,
          "y": 0
        },
        {
          "x": 0.8990625,
          "y": -4.25
        },
        {
          "x": 0.8990625,
          "y": -3.0500000000000007
        },
        {
          "x": 0,
          "y": 0
        }
      ]
    },
    {
      "SourcePinAddress": {
        "PinID": 0,
        "PinOwnerID": 774388812
      },
      "TargetPinAddress": {
        "PinID": 1367873140,
        "PinOwnerID": 1892717237
      },
      "ConnectionType": 0,
      "ConnectedWireIndex": -1,
      "ConnectedWireSegmentIndex": -1,
      "Points": [
        {
          "x": 0,
          "y": 0
        },
        {
          "x": 1.0274999999999999,
          "y": -4.75
        },
        {
          "x": 1.0274999999999999,
          "y": -3.250000000000001
        },
        {
          "x": 0,
          "y": 0
        }
      ]
    },
    {
      "SourcePinAddress": {
        "PinID": 0,
        "PinOwnerID": 984486587
      },
      "TargetPinAddress": {
        "PinID": 1311157128,
        "PinOwnerID": 1892717237
      },
      "ConnectionType": 0,
      "ConnectedWireIndex": -1,
      "ConnectedWireSegmentIndex": -1,
      "Points": [
        {
          "x": 0,
          "y": 0
        },
        {
          "x": 1.1559375,
          "y": -5.25
        },
        {
          "x": 1.1559375,
          "y": -3.750000000000001
        },
        {
          "x": 0,
          "y": 0
        }
      ]
    },
    {
      "SourcePinAddress": {
        "PinID": 0,
        "PinOwnerID": 180723878
      },
      "TargetPinAddress": {
        "PinID": 1367873140,
        "PinOwnerID": 888382623
      },
      "ConnectionType": 0,
      "ConnectedWireIndex": -1,
      "ConnectedWireSegmentIndex": -1,
      "Points": [
        {
          "x": 0,
          "y": 0
        },
        {
          "x": 0.5137499999999999,
          "y": -5.75
        },
        {
          "x": 0.5137499999999999,
          "y": -3.950000000000001
        },
        {
          "x": 0,
          "y": 0
        }
      ]
    },
    {
      "SourcePinAddress": {
        "PinID": 0,
        "PinOwnerID": 685411404
      },
      "TargetPinAddress": {
        "PinID": 1311157128,
        "PinOwnerID": 888382623
      },
      "ConnectionType": 0,
      "ConnectedWireIndex": -1,
      "ConnectedWireSegmentIndex": -1,
      "Points": [
        {
          "x": 0,
          "y": 0
        },
        {
          "x": 0.6421874999999999,
          "y": -6.25
        },
        {
          "x": 0.6421874999999999,
          "y": -4.450000000000001
        },
        {
          "x": 0,
          "y": 0
        }
      ]
    },
    {
      "SourcePinAddress": {
        "PinID": 0,
        "PinOwnerID": 1272759553
      },
      "TargetPinAddress": {
        "PinID": 1367873140,
        "PinOwnerID": 1298487732
      },
      "ConnectionType": 0,
      "ConnectedWireIndex": -1,
      "ConnectedWireSegmentIndex": -1,
      "Points": [
        {
          "x": 0,
          "y": 0
        },
        {
          "x": 0.7706249999999999,
          "y": -6.75
        },
        {
          "x": 0.7706249999999999,
          "y": -4.65
        },
        {
          "x": 0,
          "y": 0
        }
      ]
    },
    {
      "SourcePinAddress": {
        "PinID": 0,
        "PinOwnerID": 85966576
      },
      "TargetPinAddress": {
        "PinID": 1311157128,
        "PinOwnerID": 1298487732
      },
      "ConnectionType": 0,
      "ConnectedWireIndex": -1,
      "ConnectedWireSegmentIndex": -1,
      "Points": [
        {
          "x": 0,
          "y": 0
        },
        {
          "x": 0.8990625,
          "y": -7.25
        },
        {
          "x": 0.8990625,
          "y": -5.15
        },
        {
          "x": 0,
          "y": 0
        }
      ]
    },
    {
      "SourcePinAddress": {
        "PinID": 2075686198,
        "PinOwnerID": 1116572725
      },
      "TargetPinAddress": {
        "PinID": 1367873140,
        "PinOwnerID": 1230984279
      },
      "ConnectionType": 0,
      "ConnectedWireIndex": -1,
      "ConnectedWireSegmentIndex": -1,
      "Points": [
        {
          "x": 0,
          "y": 0
        },
        {
          "x": 2.715,
          "y": 4.8999999999999995
        },
        {
          "x": 2.715,
          "y": 2.35
        },
        {
          "x": 0,
          "y": 0
        }
      ]
    },
    {
      "SourcePinAddress": {
        "PinID": 2075686198,
        "PinOwnerID": 318589364
      },
      "TargetPinAddress": {
        "PinID": 1311157128,
        "PinOwnerID": 1230984279
      },
      "ConnectionType": 0,
      "ConnectedWireIndex": -1,
      "ConnectedWireSegmentIndex": -1,
      "Points": [
        {
          "x": 0,
          "y": 0
        },
        {
          "x": 2.821875,
          "y": 4.2
        },
        {
          "x": 2.821875,
          "y": 1.85
        },
        {
          "x": 0,
          "y": 0
        }
      ]
    },
    {
      "SourcePinAddress": {
        "PinID": 2075686198,
        "PinOwnerID": 1120125273
      },
      "TargetPinAddress": {
        "PinID": 1367873140,
        "PinOwnerID": 1009138828
      },
      "ConnectionType": 0,
      "ConnectedWireIndex": -1,
      "ConnectedWireSegmentIndex": -1,
      "Points": [
        {
          "x": 0,
          "y": 0
        },
        {
          "x": 2.92875,
          "y": 3.5
        },
        {
          "x": 2.92875,
          "y": 1.65
        },
        {
          "x": 0,
          "y": 0
        }
      ]
    },
    {
      "SourcePinAddress": {
        "PinID": 2075686198,
        "PinOwnerID": 769852393
      },
      "TargetPinAddress": {
        "PinID": 1311157128,
        "PinOwnerID": 1009138828
      },
      "ConnectionType": 0,
      "ConnectedWireIndex": -1,
      "ConnectedWireSegmentIndex": -1,
      "Points": [
        {
          "x": 0,
          "y": 0
        },
        {
          "x": 3.035625,
          "y": 2.8
        },
        {
          "x": 3.035625,
          "y": 1.15
        },
        {
          "x": 0,
          "y": 0
        }
      ]
    },
    {
      "SourcePinAddress": {
        "PinID": 2075686198,
        "PinOwnerID": 68666773
      },
      "TargetPinAddress": {
        "PinID": 1367873140,
        "PinOwnerID": 865562477
      },
      "ConnectionType": 0,
      "ConnectedWireIndex": -1,
      "ConnectedWireSegmentIndex": -1,
      "Points": [
        {
          "x": 0,
          "y": 0
        },
        {
          "x": 3.1425,
          "y": 2.0999999999999996
        },
        {
          "x": 3.1425,
          "y": 0.9499999999999998
        },
        {
          "x": 0,
          "y": 0
        }
      ]
    },
    {
      "SourcePinAddress": {
        "PinID": 2075686198,
        "PinOwnerID": 795275260
      },
      "TargetPinAddress": {
        "PinID": 1311157128,
        "PinOwnerID": 865562477
      },
      "ConnectionType": 0,
      "ConnectedWireIndex": -1,
      "ConnectedWireSegmentIndex": -1,
      "Points": [
        {
          "x": 0,
          "y": 0
        },
        {
          "x": 3.249375,
          "y": 1.3999999999999995
        },
        {
          "x": 3.249375,
          "y": 0.44999999999999984
        },
        {
          "x": 0,
          "y": 0
        }
      ]
    },
    {
      "SourcePinAddress": {
        "PinID": 2075686198,
        "PinOwnerID": 1715354987
      },
      "TargetPinAddress": {
        "PinID": 1367873140,
        "PinOwnerID": 1541698629
      },
      "ConnectionType": 0,
      "ConnectedWireIndex": -1,
      "ConnectedWireSegmentIndex": -1,
      "Points": [
        {
          "x": 0,
          "y": 0
        },
        {
          "x": 2.715,
          "y": 0.6999999999999994
        },
        {
          "x": 2.715,
          "y": 0.2499999999999999
        },
        {
          "x": 0,
          "y": 0
        }
      ]
    },
    {
      "SourcePinAddress": {
        "PinID": 2075686198,
        "PinOwnerID": 1016307063
      },
      "TargetPinAddress": {
        "PinID": 1311157128,
        "PinOwnerID": 1541698629
      },
      "ConnectionType": 0,
      "ConnectedWireIndex": -1,
      "ConnectedWireSegmentIndex": -1,
      "Points": [
        {
          "x": 0,
          "y": 0
        },
        {
          "x": 2.821875,
          "y": -5.551115123125783e-16
        },
        {
          "x": 2.821875,
          "y": -0.2500000000000001
        },
        {
          "x": 0,
          "y": 0
        }
      ]
    },
    {
      "SourcePinAddress": {
        "PinID": 2075686198,
        "PinOwnerID": 126803588
      },
      "TargetPinAddress": {
        "PinID": 1367873140,
        "PinOwnerID": 1003649762
      },
      "ConnectionType": 0,
      "ConnectedWireIndex": -1,
      "ConnectedWireSegmentIndex": -1,
      "Points": [
        {
          "x": 0,
          "y": 0
        },
        {
          "x": 2.92875,
          "y": -0.7000000000000005
        },
        {
          "x": 2.92875,
          "y": -0.45000000000000007
        },
        {
          "x": 0,
          "y": 0
        }
      ]
    },
    {
      "SourcePinAddress": {
        "PinID": 2075686198,
        "PinOwnerID": 1469145571
      },
      "TargetPinAddress": {
        "PinID": 1311157128,
        "PinOwnerID": 1003649762
      },
      "ConnectionType": 0,
      "ConnectedWireIndex": -1,
      "ConnectedWireSegmentIndex": -1,
      "Points": [
        {
          "x": 0,
          "y": 0
        },
        {
          "x": 3.035625,
          "y": -1.4000000000000004
        },
        {
          "x": 3.035625,
          "y": -0.9500000000000001
        },
        {
          "x": 0,
          "y": 0
        }
      ]
    },
    {
      "SourcePinAddress": {
        "PinID": 2075686198,
        "PinOwnerID": 1025654058
      },
      "TargetPinAddress": {
        "PinID": 1367873140,
        "PinOwnerID": 164299224
      },
      "ConnectionType": 0,
      "ConnectedWireIndex": -1,
      "ConnectedWireSegmentIndex": -1,
      "Points": [
        {
          "x": 0,
          "y": 0
        },
        {
          "x": 3.1425,
          "y": -2.1000000000000005
        },
        {
          "x": 3.1425,
          "y": -1.15
        },
        {
          "x": 0,
          "y": 0
        }
      ]
    },
    {
      "SourcePinAddress": {
        "PinID": 2075686198,
        "PinOwnerID": 1204463035
      },
      "TargetPinAddress": {
        "PinID": 1311157128,
        "PinOwnerID": 164299224
      },
      "ConnectionType": 0,
      "ConnectedWireIndex": -1,
      "ConnectedWireSegmentIndex": -1,
      "Points": [
        {
          "x": 0,
          "y": 0
        },
        {
          "x": 3.249375,
          "y": -2.8000000000000007
        },
        {
          "x": 3.249375,
          "y": -1.65
        },
        {
          "x": 0,
          "y": 0
        }
      ]
    },
    {
      "SourcePinAddress": {
        "PinID": 2075686198,
        "PinOwnerID": 1892717237
      },
      "TargetPinAddress": {
        "PinID": 1367873140,
        "PinOwnerID": 308888300
      },
      "ConnectionType": 0,
      "ConnectedWireIndex": -1,
      "ConnectedWireSegmentIndex": -1,
      "Points": [
        {
          "x": 0,
          "y": 0
        },
        {
          "x": 2.715,
          "y": -3.500000000000001
        },
        {
          "x": 2.715,
          "y": -1.85
        },
        {
          "x": 0,
          "y": 0
        }
      ]
    },
    {
      "SourcePinAddress": {
        "PinID": 2075686198,
        "PinOwnerID": 888382623
      },
      "TargetPinAddress": {
        "PinID": 1311157128,
        "PinOwnerID": 308888300
      },
      "ConnectionType": 0,
      "ConnectedWireIndex": -1,
      "ConnectedWireSegmentIndex": -1,
      "Points": [
        {
          "x": 0,
          "y": 0
        },
        {
          "x": 2.821875,
          "y": -4.200000000000001
        },
        {
          "x": 2.821875,
          "y": -2.35
        },
        {
          "x": 0,
          "y": 0
        }
      ]
    },
    {
      "SourcePinAddress": {
        "PinID": 2075686198,
        "PinOwnerID": 1230984279
      },
      "TargetPinAddress": {
        "PinID": 1367873140,
        "PinOwnerID": 1744496387
      },
      "ConnectionType": 0,
      "ConnectedWireIndex": -1,
      "ConnectedWireSegmentIndex": -1,
      "Points": [
        {
          "x": 0,
          "y": 0
        },
        {
          "x": 4.715,
          "y": 2.1
        },
        {
          "x": 4.715,
          "y": 1.2999999999999998
        },
        {
          "x": 0,
          "y": 0
        }
      ]
    },
    {
      "SourcePinAddress": {
        "PinID": 2075686198,
        "PinOwnerID": 1009138828
      },
      "TargetPinAddress": {
        "PinID": 1311157128,
        "PinOwnerID": 1744496387
      },
      "ConnectionType": 0,
      "ConnectedWireIndex": -1,
      "ConnectedWireSegmentIndex": -1,
      "Points": [
        {
          "x": 0,
          "y": 0
        },
        {
          "x": 4.821875,
          "y": 1.4
        },
        {
          "x": 4.821875,
          "y": 0.7999999999999998
        },
        {
          "x": 0,
          "y": 0
        }
      ]
    },
    {
      "SourcePinAddress": {
        "PinID": 2075686198,
        "PinOwnerID": 865562477
      },
      "TargetPinAddress": {
        "PinID": 1367873140,
        "PinOwnerID": 1485368144
      },
      "ConnectionType": 0,
      "ConnectedWireIndex": -1,
      "ConnectedWireSegmentIndex": -1,
      "Points": [
        {
          "x": 0,
          "y": 0
        },
        {
          "x": 4.92875,
          "y": 0.6999999999999998
        },
        {
          "x": 4.92875,
          "y": 0.5999999999999999
        },
        {
          "x": 0,
          "y": 0
        }
      ]
    },
    {
      "SourcePinAddress": {
        "PinID": 2075686198,
        "PinOwnerID": 1541698629
      },
      "TargetPinAddress": {
        "PinID": 1311157128,
        "PinOwnerID": 1485368144
      },
      "ConnectionType": 0,
      "ConnectedWireIndex": -1,
      "ConnectedWireSegmentIndex": -1,
      "Points": [
        {
          "x": 0,
          "y": 0
        },
        {
          "x": 5.035625,
          "y": -1.1102230246251565e-16
        },
        {
          "x": 5.035625,
          "y": 0.09999999999999987
        },
        {
          "x": 0,
          "y": 0
        }
      ]
    },
    {
      "SourcePinAddress": {
        "PinID": 2075686198,
        "PinOwnerID": 1003649762
      },
      "TargetPinAddress": {
        "PinID": 1367873140,
        "PinOwnerID": 1611270583
      },
      "ConnectionType": 0,
      "ConnectedWireIndex": -1,
      "ConnectedWireSegmentIndex": -1,
      "Points": [
        {
          "x": 0,
          "y": 0
        },
        {
          "x": 5.1425,
          "y": -0.7000000000000001
        },
        {
          "x": 5.1425,
          "y": -0.10000000000000009
        },
        {
          "x": 0,
          "y": 0
        }
      ]
    },
    {
      "SourcePinAddress": {
        "PinID": 2075686198,
        "PinOwnerID": 164299224
      },
      "TargetPinAddress": {
        "PinID": 1311157128,
        "PinOwnerID": 1611270583
      },
      "ConnectionType": 0,
      "ConnectedWireIndex": -1,
      "ConnectedWireSegmentIndex": -1,
      "Points": [
        {
          "x": 0,
          "y": 0
        },
        {
          "x": 5.249375000000001,
          "y": -1.4
        },
        {
          "x": 5.249375000000001,
          "y": -0.6000000000000001
        },
        {
          "x": 0,
          "y": 0
        }
      ]
    },
    {
      "SourcePinAddress": {
        "PinID": 2075686198,
        "PinOwnerID": 308888300
      },
      "TargetPinAddress": {
        "PinID": 1367873140,
        "PinOwnerID": 2020794374
      },
      "ConnectionType": 0,
      "ConnectedWireIndex": -1,
      "ConnectedWireSegmentIndex": -1,
      "Points": [
        {
          "x": 0,
          "y": 0
        },
        {
          "x": 4.715,
          "y": -2.1
        },
        {
          "x": 4.715,
          "y": -0.8
        },
        {
          "x": 0,
          "y": 0
        }
      ]
    },
    {
      "SourcePinAddress": {
        "PinID": 2075686198,
        "PinOwnerID": 1298487732
      },
      "TargetPinAddress": {
        "PinID": 1311157128,
        "PinOwnerID": 2020794374
      },
      "ConnectionType": 0,
      "ConnectedWireIndex": -1,
      "ConnectedWireSegmentIndex": -1,
      "Points": [
        {
          "x": 0,
          "y": 0
        },
        {
          "x": 3.3150000000000004,
          "y": -4.9
        },
        {
          "x": 3.3150000000000004,
          "y": -1.3
        },
        {
          "x": 0,
          "y": 0
        }
      ]
    },
    {
      "SourcePinAddress": {
        "PinID": 2075686198,
        "PinOwnerID": 1744496387
      },
      "TargetPinAddress": {
        "PinID": 1367873140,
        "PinOwnerID": 953573564
      },
      "ConnectionType": 0,
      "ConnectedWireIndex": -1,
      "ConnectedWireSegmentIndex": -1,
      "Points": [
        {
          "x": 0,
          "y": 0
        },
        {
          "x": 6.715,
          "y": 1.0499999999999998
        },
        {
          "x": 6.715,
          "y": 0.6
        },
        {
          "x": 0,
          "y": 0
        }
      ]
    },
    {
      "SourcePinAddress": {
        "PinID": 2075686198,
        "PinOwnerID": 1485368144
      },
      "TargetPinAddress": {
        "PinID": 1311157128,
        "PinOwnerID": 953573564
      },
      "ConnectionType": 0,
      "ConnectedWireIndex": -1,
      "ConnectedWireSegmentIndex": -1,
      "Points": [
        {
          "x": 0,
          "y": 0
        },
        {
          "x": 6.821875,
          "y": 0.34999999999999987
        },
        {
          "x": 6.821875,
          "y": 0.09999999999999998
        },
        {
          "x": 0,
          "y": 0
        }
      ]
    },
    {
      "SourcePinAddress": {
        "PinID": 2075686198,
        "PinOwnerID": 1611270583
      },
      "TargetPinAddress": {
        "PinID": 1367873140,
        "PinOwnerID": 1387814447
      },
      "ConnectionType": 0,
      "ConnectedWireIndex": -1,
      "ConnectedWireSegmentIndex": -1,
      "Points": [
        {
          "x": 0,
          "y": 0
        },
        {
          "x": 6.92875,
          "y": -0.3500000000000001
        },
        {
          "x": 6.92875,
          "y": -0.09999999999999998
        },
        {
          "x": 0,
          "y": 0
        }
      ]
    },
    {
      "SourcePinAddress": {
        "PinID": 2075686198,
        "PinOwnerID": 2020794374
      },
      "TargetPinAddress": {
        "PinID": 1311157128,
        "PinOwnerID": 1387814447
      },
      "ConnectionType": 0,
      "ConnectedWireIndex": -1,
      "ConnectedWireSegmentIndex": -1,
      "Points": [
        {
          "x": 0,
          "y": 0
        },
        {
          "x": 7.035625,
          "y": -1.05
        },
        {
          "x": 7.035625,
          "y": -0.6
        },
        {
          "x": 0,
          "y": 0
        }
      ]
    },
    {
      "SourcePinAddress": {
        "PinID": 2075686198,
        "PinOwnerID": 953573564
      },
      "TargetPinAddress": {
        "PinID": 1367873140,
        "PinOwnerID": 394161708
      },
      "ConnectionType": 0,
      "ConnectedWireIndex": -1,
      "ConnectedWireSegmentIndex": -1,
      "Points": [
        {
          "x": 0,
          "y": 0
        },
        {
          "x": 8.715,
          "y": 0.35
        },
        {
          "x": 8.715,
          "y": 0.25
        },
        {
          "x": 0,
          "y": 0
        }
      ]
    },
    {
      "SourcePinAddress": {
        "PinID": 2075686198,
        "PinOwnerID": 1387814447
      },
      "TargetPinAddress": {
        "PinID": 1311157128,
        "PinOwnerID": 394161708
      },
      "ConnectionType": 0,
      "ConnectedWireIndex": -1,
      "ConnectedWireSegmentIndex": -1,
      "Points": [
        {
          "x": 0,
          "y": 0
        },
        {
          "x": 8.821875,
          "y": -0.35
        },
        {
          "x": 8.821875,
          "y": -0.25
        },
        {
          "x": 0,
          "y": 0
        }
      ]
    },
    {
      "SourcePinAddress": {
        "PinID": 2075686198,
        "PinOwnerID": 394161708
      },
      "TargetPinAddress": {
        "PinID": 1499227601,
        "PinOwnerID": 1407689217
      },
      "ConnectionType": 0,
      "ConnectedWireIndex": -1,
      "ConnectedWireSegmentIndex": -1,
      "Points": [
        {
          "x": 0,
          "y": 0
        },
        {
          "x": 0,
          "y": 0
        }
      ]
    },
    {
      "SourcePinAddress": {
        "PinID": 528329037,
        "PinOwnerID": 1407689217
      },
      "TargetPinAddress": {
        "PinID": 0,
        "PinOwnerID": 1698926522
      },
      "ConnectionType": 0,
      "ConnectedWireIndex": -1,
      "ConnectedWireSegmentIndex": -1,
      "Points": [
        {
          "x": 0,
          "y": 0
        },
        {
          "x": 0,
          "y": 0
        }
      ]
    }
  ],
  "Displays": []
}