{
  "DLSVersion": "2.1.6",
  "Name": "SISO-27",
  "NameLocation": 0,
  "ChipType": 0,
  "Size": {
    "x": 1.8,
    "y": 0.6
  },
  "Colour": {
    "r": 0.5882352941176471,
    "g": 0.4,
    "b": 0.25098039215686274,
    "a": 1
  },
  "InputPins": [
    {
      "Name": "SER",
      "ID": 1595212815,
      "Position": {
        "x": 0,
        "y": 0.25
      },
      "BitCount": 1,
      "Colour": 0,
      "ValueDisplayMode": 0
    },
    {
      "Name": "CLK",
      "ID": 1602089933,
      "Position": {
        "x": 0,
        "y": -0.25
      },
      "BitCount": 1,
      "Colour": 0,
      "ValueDisplayMode": 0
    }
  ],
  "OutputPins": [
    {
      "Name": "OUT",
      "ID": 924941012,
      "Position": {
        "x": 56,
        "y": 0
      },
      "BitCount": 1,
      "Colour": 0,
      "ValueDisplayMode": 0
    }
  ],
  "SubChips": [
    {
      "Name": "D-FF",
      "ID": 1035406981,
      "Label": "",
      "Position": {
        "x": 2,
        "y": 0
      },
      "OutputPinColourInfo": [
        {
          "PinColour": 0,
          "PinID": 2089984820
        },
        {
          "PinColour": 0,
          "PinID": 1587401415
        }
      ],
      "InternalData": null
    },
    {
      "Name": "D-FF",
      "ID": 219196810,
      "Label": "",
      "Position": {
        "x": 4,
        "y": 0
      },
      "OutputPinColourInfo": [
        {
          "PinColour": 0,
          "PinID": 2089984820
        },
        {
          "PinColour": 0,
          "PinID": 1587401415
        }
      ],
      "InternalData": null
    },
    {
      "Name": "D-FF",
      "ID": 869276453,
      "Label": "",
      "Position": {
        "x": 6,
        "y": 0
      },
      "OutputPinColourInfo": [
        {
          "PinColour": 0,
          "PinID": 2089984820
        },
        {
          "PinColour": 0,
          "PinID": 1587401415
        }
      ],
      "InternalData": null
    },
    {
      "Name": "D-FF",
      "ID": 114965854,
      "Label": "",
      "Position": {
        "x": 8,
        "y": 0
      },
      "OutputPinColourInfo": [
        {
          "PinColour": 0,
          "PinID": 2089984820
        },
        {
          "PinColour": 0,
          "PinID": 1587401415
        }
      ],
      "InternalData": null
    },
    {
      "Name": "D-FF",
      "ID": 1298959652,
      "Label": "",
      "Position": {
        "x": 10,
        "y": 0
      },
      "OutputPinColourInfo": [
        {
          "PinColour": 0,
          "PinID": 2089984820
        },
        {
          "PinColour": 0,
          "PinID": 1587401415
        }
      ],
      "InternalData": null
    },
    {
      "Name": "D-FF",
      "ID": 1237391912,
      "Label": "",
      "Position": {
        "x": 12,
        "y": 0
      },
      "OutputPinColourInfo": [
        {
          "PinColour": 0,
          "PinID": 2089984820
        },
        {
          "PinColour": 0,
          "PinID": 1587401415
        }
      ],
      "InternalData": null
    },
    {
      "Name": "D-FF",
      "ID": 1526427457,
      "Label": "",
      "Position": {
        "x": 14,
        "y": 0
      },
      "OutputPinColourInfo": [
        {
          "PinColour": 0,
          "PinID": 2089984820
        },
        {
          "PinColour": 0,
          "PinID": 1587401415
        }
      ],
      "InternalData": null
    },
    {
      "Name": "D-FF",
      "ID": 1547457878,
      "Label": "",
      "Position": {
        "x": 16,
        "y": 0
      },
      "OutputPinColourInfo": [
        {
          "PinColour": 0,
          "PinID": 2089984820
        },
        {
          "PinColour": 0,
          "PinID": 1587401415
        }
      ],
      "InternalData": null
    },
    {
      "Name": "D-FF",
      "ID": 1863739734,
      "Label": "",
      "Position": {
        "x": 18,
        "y": 0
      },
      "OutputPinColourInfo": [
        {
          "PinColour": 0,
          "PinID": 2089984820
        },
        {
          "PinColour": 0,
          "PinID": 1587401415
        }
      ],
      "InternalData": null
    },
    {
      "Name": "D-FF",
      "ID": 586026999,
      "Label": "",
      "Position": {
        "x": 20,
        "y": 0
      },
      "OutputPinColourInfo": [
        {
          "PinColour": 0,
          "PinID": 2089984820
        },
        {
          "PinColour": 0,
          "PinID": 1587401415
        }
      ],
      "InternalData": null
    },
    {
      "Name": "D-FF",
      "ID": 1339830912,
      "Label": "",
      "Position": {
        "x": 22,
        "y": 0
      },
      "OutputPinColourInfo": [
        {
          "PinColour": 0,
          "PinID": 2089984820
        },
        {
          "PinColour": 0,
          "PinID": 1587401415
        }
      ],
      "InternalData": null
    },
    {
      "Name": "D-FF",
      "ID": 1418119403,
      "Label": "",
      "Position": {
        "x": 24,
        "y": 0
      },
      "OutputPinColourInfo": [
        {
          "PinColour": 0,
          "PinID": 2089984820
        },
        {
          "PinColour": 0,
          "PinID": 1587401415
        }
      ],
      "InternalData": null
    },
    {
      "Name": "D-FF",
      "ID": 13988020,
      "Label": "",
      "Position": {
        "x": 26,
        "y": 0
      },
      "OutputPinColourInfo": [
        {
          "PinColour": 0,
          "PinID": 2089984820
        },
        {
          "PinColour": 0,
          "PinID": 1587401415
        }
      ],
      "InternalData": null
    },
    {
      "Name": "D-FF",
      "ID": 681574127,
      "Label": "",
      "Position": {
        "x": 28,
        "y": 0
      },
      "OutputPinColourInfo": [
        {
          "PinColour": 0,
          "PinID": 2089984820
        },
        {
          "PinColour": 0,
          "PinID": 1587401415
        }
      ],
      "InternalData": null
    },
    {
      "Name": "D-FF",
      "ID": 1139745994,
      "Label": "",
      "Position": {
        "x": 30,
        "y": 0
      },
      "OutputPinColourInfo": [
        {
          "PinColour": 0,
          "PinID": 2089984820
        },
        {
          "PinColour": 0,
          "PinID": 1587401415
        }
      ],
      "InternalData": null
    },
    {
      "Name": "D-FF",
      "ID": 2105148630,
      "Label": "",
      "Position": {
        "x": 32,
        "y": 0
      },
      "OutputPinColourInfo": [
        {
          "PinColour": 0,
          "PinID": 2089984820
        },
        {
          "PinColour": 0,
          "PinID": 1587401415
        }
      ],
      "InternalData": null
    },
    {
      "Name": "D-FF",
      "ID": 2143724516,
      "Label": "",
      "Position": {
        "x": 34,
        "y": 0
      },
      "OutputPinColourInfo": [
        {
          "PinColour": 0,
          "PinID": 2089984820
        },
        {
          "PinColour": 0,
          "PinID": 1587401415
        }
      ],
      "InternalData": null
    },
    {
      "Name": "D-FF",
      "ID": 1041512254,
      "Label": "",
      "Position": {
        "x": 36,
        "y": 0
      },
      "OutputPinColourInfo": [
        {
          "PinColour": 0,
          "PinID": 2089984820
        },
        {
          "PinColour": 0,
          "PinID": 1587401415
        }
      ],
      "InternalData": null
    },
    {
      "Name": "D-FF",
      "ID": 1870747371,
      "Label": "",
      "Position": {
        "x": 38,
        "y": 0
      },
      "OutputPinColourInfo": [
        {
          "PinColour": 0,
          "PinID": 2089984820
        },
        {
          "PinColour": 0,
          "PinID": 1587401415
        }
      ],
      "InternalData": null
    },
    {
      "Name": "D-FF",
      "ID": 202594217,
      "Label": "",
      "Position": {
        "x": 40,
        "y": 0
      },
      "OutputPinColourInfo": [
        {
          "PinColour": 0,
          "PinID": 2089984820
        },
        {
          "PinColour": 0,
          "PinID": 1587401415
        }
      ],
      "InternalData": null
    },
    {
      "Name": "D-FF",
      "ID": 1125482634,
      "Label": "",
      "Position": {
        "x": 42,
        "y": 0
      },
      "OutputPinColourInfo": [
        {
          "PinColour": 0,
          "PinID": 2089984820
        },
        {
          "PinColour": 0,
          "PinID": 1587401415
        }
      ],
      "InternalData": null
    },
    {
      "Name": "D-FF",
      "ID": 1244487231,
      "Label": "",
      "Position": {
        "x": 44,
        "y": 0
      },
      "OutputPinColourInfo": [
        {
          "PinColour": 0,
          "PinID": 2089984820
        },
        {
          "PinColour": 0,
          "PinID": 1587401415
        }
      ],
      "InternalData": null
    },
    {
      "Name": "D-FF",
      "ID": 994751358,
      "Label": "",
      "Position": {
        "x": 46,
        "y": 0
      },
      "OutputPinColourInfo": [
        {
          "PinColour": 0,
          "PinID": 2089984820
        },
        {
          "PinColour": 0,
          "PinID": 1587401415
        }
      ],
      "InternalData": null
    },
    {
      "Name": "D-FF",
      "ID": 837517774,
      "Label": "",
      "Position": {
        "x": 48,
        "y": 0
      },
      "OutputPinColourInfo": [
        {
          "PinColour": 0,
          "PinID": 2089984820
        },
        {
          "PinColour": 0,
          "PinID": 1587401415
        }
      ],
      "InternalData": null
    },
    {
      "Name": "D-FF",
      "ID": 1201132302,
      "Label": "",
      "Position": {
        "x": 50,
        "y": 0
      },
      "OutputPinColourInfo": [
        {
          "PinColour": 0,
          "PinID": 2089984820
        },
        {
          "PinColour": 0,
          "PinID": 1587401415
        }
      ],
      "InternalData": null
    },
    {
      "Name": "D-FF",
      "ID": 126893611,
      "Label": "",
      "Position": {
        "x": 52,
        "y": 0
      },
      "OutputPinColourInfo": [
        {
          "PinColour": 0,
          "PinID": 2089984820
        },
        {
          "PinColour": 0,
          "PinID": 1587401415
        }
      ],
      "InternalData": null
    },
    {
      "Name": "D-FF",
      "ID": 621904062,
      "Label": "",
      "Position": {
        "x": 54,
        "y": 0
      },
      "OutputPinColourInfo": [
        {
          "PinColour": 0,
          "PinID": 2089984820
        },
        {
          "PinColour": 0,
          "PinID": 1587401415
        }
      ],
      "InternalData": null
    }
  ],
  "Wires": [
    {
      "SourcePinAddress": {
        "PinID": 0,
        "PinOwnerID": 1595212815
      },
      "TargetPinAddress": {
        "PinID": 880850201,
        "PinOwnerID": 1035406981
      },
      "ConnectionType": 0,
      "ConnectedWireIndex": -1,
      "ConnectedWireSegmentIndex": -1,
      "Points": [
        {
          "x": 0,
          "y": 0
        },
        {
          "x": 0,
          "y": 0
        }
      ]
    },
    {
      "SourcePinAddress": {
        "PinID": 0,
        "PinOwnerID": 1602089933
      },
      "TargetPinAddress": {
        "PinID": 2046145189,
        "PinOwnerID": 1035406981
      },
      "ConnectionType": 0,
      "ConnectedWireIndex": -1,
      "ConnectedWireSegmentIndex": -1,
      "Points": [
        {
          "x": 0,
          "y": 0
        },
        {
          "x": 0,
          "y": 0
        }
      ]
    },
    {
      "SourcePinAddress": {
        "PinID": 2089984820,
        "PinOwnerID": 1035406981
      },
      "TargetPinAddress": {
        "PinID": 880850201,
        "PinOwnerID": 219196810
      },
      "ConnectionType": 0,
      "ConnectedWireIndex": -1,
      "ConnectedWireSegmentIndex": -1,
      "Points": [
        {
          "x": 0,
          "y": 0
        },
        {
          "x": 0,
          "y": 0
        }
      ]
    },
    {
      "SourcePinAddress": {
        "PinID": 0,
        "PinOwnerID": 1602089933
      },
      "TargetPinAddress": {
        "PinID": 2046145189,
        "PinOwnerID": 219196810
      },
      "ConnectionType": 0,
      "ConnectedWireIndex": -1,
      "ConnectedWireSegmentIndex": -1,
      "Points": [
        {
          "x": 0,
          "y": 0
        },
        {
          "x": 0,
          "y": 0
        }
      ]
    },
    {
      "SourcePinAddress": {
        "PinID": 2089984820,
        "PinOwnerID": 219196810
      },
      "TargetPinAddress": {
        "PinID": 880850201,
        "PinOwnerID": 869276453
      },
      "ConnectionType": 0,
      "ConnectedWireIndex": -1,
      "ConnectedWireSegmentIndex": -1,
      "Points": [
        {
          "x": 0,
          "y": 0
        },
        {
          "x": 0,
          "y": 0
        }
      ]
    },
    {
      "SourcePinAddress": {
        "PinID": 0,
        "PinOwnerID": 1602089933
      },
      "TargetPinAddress": {
        "PinID": 2046145189,
        "PinOwnerID": 869276453
      },
      "ConnectionType": 0,
      "ConnectedWireIndex": -1,
      "ConnectedWireSegmentIndex": -1,
      "Points": [
        {
          "x": 0,
          "y": 0
        },
        {
          "x": 0,
          "y": 0
        }
      ]
    },
    {
      "SourcePinAddress": {
        "PinID": 2089984820,
        "PinOwnerID": 869276453
      },
      "TargetPinAddress": {
        "PinID": 880850201,
        "PinOwnerID": 114965854
      },
      "ConnectionType": 0,
      "ConnectedWireIndex": -1,
      "ConnectedWireSegmentIndex": -1,
      "Points": [
        {
          "x": 0,
          "y": 0
        },
        {
          "x": 0,
          "y": 0
        }
      ]
    },
    {
      "SourcePinAddress": {
        "PinID": 0,
        "PinOwnerID": 1602089933
      },
      "TargetPinAddress": {
        "PinID": 2046145189,
        "PinOwnerID": 114965854
      },
      "ConnectionType": 0,
      "ConnectedWireIndex": -1,
      "ConnectedWireSegmentIndex": -1,
      "Points": [
        {
          "x": 0,
          "y": 0
        },
        {
          "x": 0,
          "y": 0
        }
      ]
    },
    {
      "SourcePinAddress": {
        "PinID": 2089984820,
        "PinOwnerID": 114965854
      },
      "TargetPinAddress": {
        "PinID": 880850201,
        "PinOwnerID": 1298959652
      },
      "ConnectionType": 0,
      "ConnectedWireIndex": -1,
      "ConnectedWireSegmentIndex": -1,
      "Points": [
        {
          "x": 0,
          "y": 0
        },
        {
          "x": 0,
          "y": 0
        }
      ]
    },
    {
      "SourcePinAddress": {
        "PinID": 0,
        "PinOwnerID": 1602089933
      },
      "TargetPinAddress": {
        "PinID": 2046145189,
        "PinOwnerID": 1298959652
      },
      "ConnectionType": 0,
      "ConnectedWireIndex": -1,
      "ConnectedWireSegmentIndex": -1,
      "Points": [
        {
          "x": 0,
          "y": 0
        },
        {
          "x": 0,
          "y": 0
        }
      ]
    },
    {
      "SourcePinAddress": {
        "PinID": 2089984820,
        "PinOwnerID": 1298959652
      },
      "TargetPinAddress": {
        "PinID": 880850201,
        "PinOwnerID": 1237391912
      },
      "ConnectionType": 0,
      "ConnectedWireIndex": -1,
      "ConnectedWireSegmentIndex": -1,
      "Points": [
        {
          "x": 0,
          "y": 0
        },
        {
          "x": 0,
          "y": 0
        }
      ]
    },
    {
      "SourcePinAddress": {
        "PinID": 0,
        "PinOwnerID": 1602089933
      },
      "TargetPinAddress": {
        "PinID": 2046145189,
        "PinOwnerID": 1237391912
      },
      "ConnectionType": 0,
      "ConnectedWireIndex": -1,
      "ConnectedWireSegmentIndex": -1,
      "Points": [
        {
          "x": 0,
          "y": 0
        },
        {
          "x": 0,
          "y": 0
        }
      ]
    },
    {
      "SourcePinAddress": {
        "PinID": 2089984820,
        "PinOwnerID": 1237391912
      },
      "TargetPinAddress": {
        "PinID": 880850201,
        "PinOwnerID": 1526427457
      },
      "ConnectionType": 0,
      "ConnectedWireIndex": -1,
      "ConnectedWireSegmentIndex": -1,
      "Points": [
        {
          "x": 0,
          "y": 0
        },
        {
          "x": 0,
          "y": 0
        }
      ]
    },
    {
      "SourcePinAddress": {
        "PinID": 0,
        "PinOwnerID": 1602089933
      },
      "TargetPinAddress": {
        "PinID": 2046145189,
        "PinOwnerID": 1526427457
      },
      "ConnectionType": 0,
      "ConnectedWireIndex": -1,
      "ConnectedWireSegmentIndex": -1,
      "Points": [
        {
          "x": 0,
          "y": 0
        },
        {
          "x": 0,
          "y": 0
        }
      ]
    },
    {
      "SourcePinAddress": {
        "PinID": 2089984820,
        "PinOwnerID": 1526427457
      },
      "TargetPinAddress": {
        "PinID": 880850201,
        "PinOwnerID": 1547457878
      },
      "ConnectionType": 0,
      "ConnectedWireIndex": -1,
      "ConnectedWireSegmentIndex": -1,
      "Points": [
        {
          "x": 0,
          "y": 0
        },
        {
          "x": 0,
          "y": 0
        }
      ]
    },
    {
      "SourcePinAddress": {
        "PinID": 0,
        "PinOwnerID": 1602089933
      },
      "TargetPinAddress": {
        "PinID": 2046145189,
        "PinOwnerID": 1547457878
      },
      "ConnectionType": 0,
      "ConnectedWireIndex": -1,
      "ConnectedWireSegmentIndex": -1,
      "Points": [
        {
          "x": 0,
          "y": 0
        },
        {
          "x": 0,
          "y": 0
        }
      ]
    },
    {
      "SourcePinAddress": {
        "PinID": 2089984820,
        "PinOwnerID": 1547457878
      },
      "TargetPinAddress": {
        "PinID": 880850201,
        "PinOwnerID": 1863739734
      },
      "ConnectionType": 0,
      "ConnectedWireIndex": -1,
      "ConnectedWireSegmentIndex": -1,
      "Points": [
        {
          "x": 0,
          "y": 0
        },
        {
          "x": 0,
          "y": 0
        }
      ]
    },
    {
      "SourcePinAddress": {
        "PinID": 0,
        "PinOwnerID": 1602089933
      },
      "TargetPinAddress": {
        "PinID": 2046145189,
        "PinOwnerID": 1863739734
      },
      "ConnectionType": 0,
      "ConnectedWireIndex": -1,
      "ConnectedWireSegmentIndex": -1,
      "Points": [
        {
          "x": 0,
          "y": 0
        },
        {
          "x": 0,
          "y": 0
        }
      ]
    },
    {
      "SourcePinAddress": {
        "PinID": 2089984820,
        "PinOwnerID": 1863739734
      },
      "TargetPinAddress": {
        "PinID": 880850201,
        "PinOwnerID": 586026999
      },
      "ConnectionType": 0,
      "ConnectedWireIndex": -1,
      "ConnectedWireSegmentIndex": -1,
      "Points": [
        {
          "x": 0,
          "y": 0
        },
        {
          "x": 0,
          "y": 0
        }
      ]
    },
    {
      "SourcePinAddress": {
        "PinID": 0,
        "PinOwnerID": 1602089933
      },
      "TargetPinAddress": {
        "PinID": 2046145189,
        "PinOwnerID": 586026999
      },
      "ConnectionType": 0,
      "ConnectedWireIndex": -1,
      "ConnectedWireSegmentIndex": -1,
      "Points": [
        {
          "x": 0,
          "y": 0
        },
        {
          "x": 0,
          "y": 0
        }
      ]
    },
    {
      "SourcePinAddress": {
        "PinID": 2089984820,
        "PinOwnerID": 586026999
      },
      "TargetPinAddress": {
        "PinID": 880850201,
        "PinOwnerID": 1339830912
      },
      "ConnectionType": 0,
      "ConnectedWireIndex": -1,
      "ConnectedWireSegmentIndex": -1,
      "Points": [
        {
          "x": 0,
          "y": 0
        },
        {
          "x": 0,
          "y": 0
        }
      ]
    },
    {
      "SourcePinAddress": {
        "PinID": 0,
        "PinOwnerID": 1602089933
      },
      "TargetPinAddress": {
        "PinID": 2046145189,
        "PinOwnerID": 1339830912
      },
      "ConnectionType": 0,
      "ConnectedWireIndex": -1,
      "ConnectedWireSegmentIndex": -1,
      "Points": [
        {
          "x": 0,
          "y": 0
        },
        {
          "x": 0,
          "y": 0
        }
      ]
    },
    {
      "SourcePinAddress": {
        "PinID": 2089984820,
        "PinOwnerID": 1339830912
      },
      "TargetPinAddress": {
        "PinID": 880850201,
        "PinOwnerID": 1418119403
      },
      "ConnectionType": 0,
      "ConnectedWireIndex": -1,
      "ConnectedWireSegmentIndex": -1,
      "Points": [
        {
          "x": 0,
          "y": 0
        },
        {
          "x": 0,
          "y": 0
        }
      ]
    },
    {
      "SourcePinAddress": {
        "PinID": 0,
        "PinOwnerID": 1602089933
      },
      "TargetPinAddress": {
        "PinID": 2046145189,
        "PinOwnerID": 1418119403
      },
      "ConnectionType": 0,
      "ConnectedWireIndex": -1,
      "ConnectedWireSegmentIndex": -1,
      "Points": [
        {
          "x": 0,
          "y": 0
        },
        {
          "x": 0,
          "y": 0
        }
      ]
    },
    {
      "SourcePinAddress": {
        "PinID": 2089984820,
        "PinOwnerID": 1418119403
      },
      "TargetPinAddress": {
        "PinID": 880850201,
        "PinOwnerID": 13988020
      },
      "ConnectionType": 0,
      "ConnectedWireIndex": -1,
      "ConnectedWireSegmentIndex": -1,
      "Points": [
        {
          "x": 0,
          "y": 0
        },
        {
          "x": 0,
          "y": 0
        }
      ]
    },
    {
      "SourcePinAddress": {
        "PinID": 0,
        "PinOwnerID": 1602089933
      },
      "TargetPinAddress": {
        "PinID": 2046145189,
        "PinOwnerID": 13988020
      },
      "ConnectionType": 0,
      "ConnectedWireIndex": -1,
      "ConnectedWireSegmentIndex": -1,
      "Points": [
        {
          "x": 0,
          "y": 0
        },
        {
          "x": 0,
          "y": 0
        }
      ]
    },
    {
      "SourcePinAddress": {
        "PinID": 2089984820,
        "PinOwnerID": 13988020
      },
      "TargetPinAddress": {
        "PinID": 880850201,
        "PinOwnerID": 681574127
      },
      "ConnectionType": 0,
      "ConnectedWireIndex": -1,
      "ConnectedWireSegmentIndex": -1,
      "Points": [
        {
          "x": 0,
          "y": 0
        },
        {
          "x": 0,
          "y": 0
        }
      ]
    },
    {
      "SourcePinAddress": {
        "PinID": 0,
        "PinOwnerID": 1602089933
      },
      "TargetPinAddress": {
        "PinID": 2046145189,
        "PinOwnerID": 681574127
      },
      "ConnectionType": 0,
      "ConnectedWireIndex": -1,
      "ConnectedWireSegmentIndex": -1,
      "Points": [
        {
          "x": 0,
          "y": 0
        },
        {
          "x": 0,
          "y": 0
        }
      ]
    },
    {
      "SourcePinAddress": {
        "PinID": 2089984820,
        "PinOwnerID": 681574127
      },
      "TargetPinAddress": {
        "PinID": 880850201,
        "PinOwnerID": 1139745994
      },
      "ConnectionType": 0,
      "ConnectedWireIndex": -1,
      "ConnectedWireSegmentIndex": -1,
      "Points": [
        {
          "x": 0,
          "y": 0
        },
        {
          "x": 0,
          "y": 0
        }
      ]
    },
    {
      "SourcePinAddress": {
        "PinID": 0,
        "PinOwnerID": 1602089933
      },
      "TargetPinAddress": {
        "PinID": 2046145189,
        "PinOwnerID": 1139745994
      },
      "ConnectionType": 0,
      "ConnectedWireIndex": -1,
      "ConnectedWireSegmentIndex": -1,
      "Points": [
        {
          "x": 0,
          "y": 0
        },
        {
          "x": 0,
          "y": 0
        }
      ]
    },
    {
      "SourcePinAddress": {
        "PinID": 2089984820,
        "PinOwnerID": 1139745994
      },
      "TargetPinAddress": {
        "PinID": 880850201,
        "PinOwnerID": 2105148630
      },
      "ConnectionType": 0,
      "ConnectedWireIndex": -1,
      "ConnectedWireSegmentIndex": -1,
      "Points": [
        {
          "x": 0,
          "y": 0
        },
        {
          "x": 0,
          "y": 0
        }
      ]
    },
    {
      "SourcePinAddress": {
        "PinID": 0,
        "PinOwnerID": 1602089933
      },
      "TargetPinAddress": {
        "PinID": 2046145189,
        "PinOwnerID": 2105148630
      },
      "ConnectionType": 0,
      "ConnectedWireIndex": -1,
      "ConnectedWireSegmentIndex": -1,
      "Points": [
        {
          "x": 0,
          "y": 0
        },
        {
          "x": 0,
          "y": 0
        }
      ]
    },
    {
      "SourcePinAddress": {
        "PinID": 2089984820,
        "PinOwnerID": 2105148630
      },
      "TargetPinAddress": {
        "PinID": 880850201,
        "PinOwnerID": 2143724516
      },
      "ConnectionType": 0,
      "ConnectedWireIndex": -1,
      "ConnectedWireSegmentIndex": -1,
      "Points": [
        {
          "x": 0,
          "y": 0
        },
        {
          "x": 0,
          "y": 0
        }
      ]
    },
    {
      "SourcePinAddress": {
        "PinID": 0,
        "PinOwnerID": 1602089933
      },
      "TargetPinAddress": {
        "PinID": 2046145189,
        "PinOwnerID": 2143724516
      },
      "ConnectionType": 0,
      "ConnectedWireIndex": -1,
      "ConnectedWireSegmentIndex": -1,
      "Points": [
        {
          "x": 0,
          "y": 0
        },
        {
          "x": 0,
          "y": 0
        }
      ]
    },
    {
      "SourcePinAddress": {
        "PinID": 2089984820,
        "PinOwnerID": 2143724516
      },
      "TargetPinAddress": {
        "PinID": 880850201,
        "PinOwnerID": 1041512254
      },
      "ConnectionType": 0,
      "ConnectedWireIndex": -1,
      "ConnectedWireSegmentIndex": -1,
      "Points": [
        {
          "x": 0,
          "y": 0
        },
        {
          "x": 0,
          "y": 0
        }
      ]
    },
    {
      "SourcePinAddress": {
        "PinID": 0,
        "PinOwnerID": 1602089933
      },
      "TargetPinAddress": {
        "PinID": 2046145189,
        "PinOwnerID": 1041512254
      },
      "ConnectionType": 0,
      "ConnectedWireIndex": -1,
      "ConnectedWireSegmentIndex": -1,
      "Points": [
        {
          "x": 0,
          "y": 0
        },
        {
          "x": 0,
          "y": 0
        }
      ]
    },
    {
      "SourcePinAddress": {
        "PinID": 2089984820,
        "PinOwnerID": 1041512254
      },
      "TargetPinAddress": {
        "PinID": 880850201,
        "PinOwnerID": 1870747371
      },
      "ConnectionType": 0,
      "ConnectedWireIndex": -1,
      "ConnectedWireSegmentIndex": -1,
      "Points": [
        {
          "x": 0,
          "y": 0
        },
        {
          "x": 0,
          "y": 0
        }
      ]
    },
    {
      "SourcePinAddress": {
        "PinID": 0,
        "PinOwnerID": 1602089933
      },
      "TargetPinAddress": {
        "PinID": 2046145189,
        "PinOwnerID": 1870747371
      },
      "ConnectionType": 0,
      "ConnectedWireIndex": -1,
      "ConnectedWireSegmentIndex": -1,
      "Points": [
        {
          "x": 0,
          "y": 0
        },
        {
          "x": 0,
          "y": 0
        }
      ]
    },
    {
      "SourcePinAddress": {
        "PinID": 2089984820,
        "PinOwnerID": 1870747371
      },
      "TargetPinAddress": {
        "PinID": 880850201,
        "PinOwnerID": 202594217
      },
      "ConnectionType": 0,
      "ConnectedWireIndex": -1,
      "ConnectedWireSegmentIndex": -1,
      "Points": [
        {
          "x": 0,
          "y": 0
        },
        {
          "x": 0,
          "y": 0
        }
      ]
    },
    {
      "SourcePinAddress": {
        "PinID": 0,
        "PinOwnerID": 1602089933
      },
      "TargetPinAddress": {
        "PinID": 2046145189,
        "PinOwnerID": 202594217
      },
      "ConnectionType": 0,
      "ConnectedWireIndex": -1,
      "ConnectedWireSegmentIndex": -1,
      "Points": [
        {
          "x": 0,
          "y": 0
        },
        {
          "x": 0,
          "y": 0
        }
      ]
    },
    {
      "SourcePinAddress": {
        "PinID": 2089984820,
        "PinOwnerID": 202594217
      },
      "TargetPinAddress": {
        "PinID": 880850201,
        "PinOwnerID": 1125482634
      },
      "ConnectionType": 0,
      "ConnectedWireIndex": -1,
      "ConnectedWireSegmentIndex": -1,
      "Points": [
        {
          "x": 0,
          "y": 0
        },
        {
          "x": 0,
          "y": 0
        }
      ]
    },
    {
      "SourcePinAddress": {
        "PinID": 0,
        "PinOwnerID": 1602089933
      },
      "TargetPinAddress": {
        "PinID": 2046145189,
        "PinOwnerID": 1125482634
      },
      "ConnectionType": 0,
      "ConnectedWireIndex": -1,
      "ConnectedWireSegmentIndex": -1,
      "Points": [
        {
          "x": 0,
          "y": 0
        },
        {
          "x": 0,
          "y": 0
        }
      ]
    },
    {
      "SourcePinAddress": {
        "PinID": 2089984820,
        "PinOwnerID": 1125482634
      },
      "TargetPinAddress": {
        "PinID": 880850201,
        "PinOwnerID": 1244487231
      },
      "ConnectionType": 0,
      "ConnectedWireIndex": -1,
      "ConnectedWireSegmentIndex": -1,
      "Points": [
        {
          "x": 0,
          "y": 0
        },
        {
          "x": 0,
          "y": 0
        }
      ]
    },
    {
      "SourcePinAddress": {
        "PinID": 0,
        "PinOwnerID": 1602089933
      },
      "TargetPinAddress": {
        "PinID": 2046145189,
        "PinOwnerID": 1244487231
      },
      "ConnectionType": 0,
      "ConnectedWireIndex": -1,
      "ConnectedWireSegmentIndex": -1,
      "Points": [
        {
          "x": 0,
          "y": 0
        },
        {
          "x": 0,
          "y": 0
        }
      ]
    },
    {
      "SourcePinAddress": {
        "PinID": 2089984820,
        "PinOwnerID": 1244487231
      },
      "TargetPinAddress": {
        "PinID": 880850201,
        "PinOwnerID": 994751358
      },
      "ConnectionType": 0,
      "ConnectedWireIndex": -1,
      "ConnectedWireSegmentIndex": -1,
      "Points": [
        {
          "x": 0,
          "y": 0
        },
        {
          "x": 0,
          "y": 0
        }
      ]
    },
    {
      "SourcePinAddress": {
        "PinID": 0,
        "PinOwnerID": 1602089933
      },
      "TargetPinAddress": {
        "PinID": 2046145189,
        "PinOwnerID": 994751358
      },
      "ConnectionType": 0,
      "ConnectedWireIndex": -1,
      "ConnectedWireSegmentIndex": -1,
      "Points": [
        {
          "x": 0,
          "y": 0
        },
        {
          "x": 0,
          "y": 0
        }
      ]
    },
    {
      "SourcePinAddress": {
        "PinID": 2089984820,
        "PinOwnerID": 994751358
      },
      "TargetPinAddress": {
        "PinID": 880850201,
        "PinOwnerID": 837517774
      },
      "ConnectionType": 0,
      "ConnectedWireIndex": -1,
      "ConnectedWireSegmentIndex": -1,
      "Points": [
        {
          "x": 0,
          "y": 0
        },
        {
          "x": 0,
          "y": 0
        }
      ]
    },
    {
      "SourcePinAddress": {
        "PinID": 0,
        "PinOwnerID": 1602089933
      },
      "TargetPinAddress": {
        "PinID": 2046145189,
        "PinOwnerID": 837517774
      },
      "ConnectionType": 0,
      "ConnectedWireIndex": -1,
      "ConnectedWireSegmentIndex": -1,
      "Points": [
        {
          "x": 0,
          "y": 0
        },
        {
          "x": 0,
          "y": 0
        }
      ]
    },
    {
      "SourcePinAddress": {
        "PinID": 2089984820,
        "PinOwnerID": 837517774
      },
      "TargetPinAddress": {
        "PinID": 880850201,
        "PinOwnerID": 1201132302
      },
      "ConnectionType": 0,
      "ConnectedWireIndex": -1,
      "ConnectedWireSegmentIndex": -1,
      "Points": [
        {
          "x": 0,
          "y": 0
        },
        {
          "x": 0,
          "y": 0
        }
      ]
    },
    {
      "SourcePinAddress": {
        "PinID": 0,
        "PinOwnerID": 1602089933
      },
      "TargetPinAddress": {
        "PinID": 2046145189,
        "PinOwnerID": 1201132302
      },
      "ConnectionType": 0,
      "ConnectedWireIndex": -1,
      "ConnectedWireSegmentIndex": -1,
      "Points": [
        {
          "x": 0,
          "y": 0
        },
        {
          "x": 0,
          "y": 0
        }
      ]
    },
    {
      "SourcePinAddress": {
        "PinID": 2089984820,
        "PinOwnerID": 1201132302
      },
      "TargetPinAddress": {
        "PinID": 880850201,
        "PinOwnerID": 126893611
      },
      "ConnectionType": 0,
      "ConnectedWireIndex": -1,
      "ConnectedWireSegmentIndex": -1,
      "Points": [
        {
          "x": 0,
          "y": 0
        },
        {
          "x": 0,
          "y": 0
        }
      ]
    },
    {
      "SourcePinAddress": {
        "PinID": 0,
        "PinOwnerID": 1602089933
      },
      "TargetPinAddress": {
        "PinID": 2046145189,
        "PinOwnerID": 126893611
      },
      "ConnectionType": 0,
      "ConnectedWireIndex": -1,
      "ConnectedWireSegmentIndex": -1,
      "Points": [
        {
          "x": 0,
          "y": 0
        },
        {
          "x": 0,
          "y": 0
        }
      ]
    },
    {
      "SourcePinAddress": {
        "PinID": 2089984820,
        "PinOwnerID": 126893611
      },
      "TargetPinAddress": {
        "PinID": 880850201,
        "PinOwnerID": 621904062
      },
      "ConnectionType": 0,
      "ConnectedWireIndex": -1,
      "ConnectedWireSegmentIndex": -1,
      "Points": [
        {
          "x": 0,
          "y": 0
        },
        {
          "x": 0,
          "y": 0
        }
      ]
    },
    {
      "SourcePinAddress": {
        "PinID": 0,
        "PinOwnerID": 1602089933
      },
      "TargetPinAddress": {
        "PinID": 2046145189,
        "PinOwnerID": 621904062
      },
      "ConnectionType": 0,
      "ConnectedWireIndex": -1,
      "ConnectedWireSegmentIndex": -1,
      "Points": [
        {
          "x": 0,
          "y": 0
        },
        {
          "x": 0,
          "y": 0
        }
      ]
    },
    {
      "SourcePinAddress": {
        "PinID": 2089984820,
        "PinOwnerID": 621904062
      },
      "TargetPinAddress": {
        "PinID": 0,
        "PinOwnerID": 924941012
      },
      "ConnectionType": 0,
      "ConnectedWireIndex": -1,
      "ConnectedWireSegmentIndex": -1,
      "Points": [
        {
          "x": 0,
          "y": 0
        },
        {
          "x": 55.09,
          "y": 0.25
        },
        {
          "x": 55.09,
          "y": 0
        },
        {
          "x": 0,
          "y": 0
        }
      ]
    }
  ],
  "Displays": []
}